pmdarima/VERSION
pmdarima/__init__.py
pmdarima/base.py
pmdarima/context_managers.py
pmdarima/decorators.py
pmdarima/metrics.py
pmdarima/pipeline.py
pmdarima/setup.py
pmdarima/warnings.py
pmdarima/__check_build/__init__.py
pmdarima/__check_build/_check_build.cpython-37m-darwin.so
pmdarima/__check_build/setup.py
pmdarima/__check_build/tests/__init__.py
pmdarima/__check_build/tests/test_check_build.py
pmdarima/_build_utils/__init__.py
pmdarima/_build_utils/pre_build_helpers.py
pmdarima/_build_utils/tests/__init__.py
pmdarima/arima/__init__.py
pmdarima/arima/_arima.cpython-37m-darwin.so
pmdarima/arima/_auto_solvers.py
pmdarima/arima/_context.py
pmdarima/arima/_doc.py
pmdarima/arima/_validation.py
pmdarima/arima/approx.py
pmdarima/arima/arima.py
pmdarima/arima/auto.py
pmdarima/arima/seasonality.py
pmdarima/arima/setup.py
pmdarima/arima/stationarity.py
pmdarima/arima/utils.py
pmdarima/arima/tests/__init__.py
pmdarima/arima/tests/test_approx.py
pmdarima/arima/tests/test_arima.py
pmdarima/arima/tests/test_arima_diagnostics.py
pmdarima/arima/tests/test_auto.py
pmdarima/arima/tests/test_auto_solvers.py
pmdarima/arima/tests/test_c_arima.py
pmdarima/arima/tests/test_context.py
pmdarima/arima/tests/test_seasonality.py
pmdarima/arima/tests/test_stationarity.py
pmdarima/arima/tests/test_utils.py
pmdarima/arima/tests/test_validation.py
pmdarima/arima/tests/data/issue_191.csv
pmdarima/compat/__init__.py
pmdarima/compat/matplotlib.py
pmdarima/compat/numpy.py
pmdarima/compat/pandas.py
pmdarima/compat/pytest.py
pmdarima/compat/sklearn.py
pmdarima/compat/statsmodels.py
pmdarima/compat/tests/__init__.py
pmdarima/compat/tests/test_sklearn.py
pmdarima/compat/tests/test_statsmodels.py
pmdarima/datasets/__init__.py
pmdarima/datasets/_base.py
pmdarima/datasets/airpassengers.py
pmdarima/datasets/ausbeer.py
pmdarima/datasets/austres.py
pmdarima/datasets/gasoline.py
pmdarima/datasets/heartrate.py
pmdarima/datasets/lynx.py
pmdarima/datasets/setup.py
pmdarima/datasets/stocks.py
pmdarima-2.0.3.dist-info/AUTHORS.md
pmdarima-2.0.3.dist-info/LICENSE
pmdarima-2.0.3.dist-info/METADATA
pmdarima-2.0.3.dist-info/WHEEL
pmdarima-2.0.3.dist-info/top_level.txt
pmdarima-2.0.3.dist-info/RECORD
