Metadata-Version: 2.1
Name: pmdarima
Version: 2.0.3
Summary: Python's forecast::auto.arima equivalent
Home-page: http://alkaline-ml.com/pmdarima
Maintainer: Taylor G. Smith
Maintainer-email: taylor.smith@alkaline-ml.com
License: MIT
Download-URL: https://pypi.org/project/pmdarima/#files
Project-URL: Bug Tracker, https://github.com/alkaline-ml/pmdarima/issues
Project-URL: Documentation, http://alkaline-ml.com/pmdarima
Project-URL: Source Code, https://github.com/alkaline-ml/pmdarima
Keywords: arima timeseries forecasting pyramid pmdarima pyramid-arima scikit-learn statsmodels
Platform: UNKNOWN
Classifier: Intended Audience :: Science/Research
Classifier: Intended Audience :: Developers
Classifier: Intended Audience :: Financial and Insurance Industry
Classifier: Programming Language :: C
Classifier: Programming Language :: Python
Classifier: Topic :: Software Development
Classifier: Topic :: Scientific/Engineering
Classifier: Operating System :: Microsoft :: Windows
Classifier: Operating System :: POSIX
Classifier: Operating System :: Unix
Classifier: Operating System :: MacOS
Classifier: Programming Language :: Python :: 3
Classifier: Programming Language :: Python :: 3.7
Classifier: Programming Language :: Python :: 3.8
Classifier: Programming Language :: Python :: 3.9
Classifier: Programming Language :: Python :: 3.10
Classifier: Programming Language :: Python :: 3.11
Classifier: Programming Language :: Python :: Implementation :: CPython
Requires-Python: >=3.7
